rapidocr/__init__.py
rapidocr/rapidocr/__init__.py
rapidocr/rapidocr/config.yaml
rapidocr/rapidocr/default_models.yaml
rapidocr/rapidocr/main.py
rapidocr/rapidocr/cal_rec_boxes/__init__.py
rapidocr/rapidocr/cal_rec_boxes/main.py
rapidocr/rapidocr/ch_ppocr_cls/__init__.py
rapidocr/rapidocr/ch_ppocr_cls/main.py
rapidocr/rapidocr/ch_ppocr_cls/utils.py
rapidocr/rapidocr/ch_ppocr_det/__init__.py
rapidocr/rapidocr/ch_ppocr_det/main.py
rapidocr/rapidocr/ch_ppocr_det/utils.py
rapidocr/rapidocr/ch_ppocr_rec/__init__.py
rapidocr/rapidocr/ch_ppocr_rec/main.py
rapidocr/rapidocr/ch_ppocr_rec/utils.py
rapidocr/rapidocr/inference_engine/__init__.py
rapidocr/rapidocr/inference_engine/base.py
rapidocr/rapidocr/inference_engine/onnxruntime.py
rapidocr/rapidocr/inference_engine/openvino.py
rapidocr/rapidocr/inference_engine/paddlepaddle.py
rapidocr/rapidocr/inference_engine/torch.py
rapidocr/rapidocr/models/ch_PP-OCRv4_det_infer.onnx
rapidocr/rapidocr/models/ch_PP-OCRv4_rec_infer.onnx
rapidocr/rapidocr/models/ch_ppocr_mobile_v2.0_cls_infer.onnx
rapidocr/rapidocr/networks/__init__.py
rapidocr/rapidocr/networks/arch_config.yaml
rapidocr/rapidocr/networks/common.py
rapidocr/rapidocr/networks/architectures/__init__.py
rapidocr/rapidocr/networks/architectures/base_model.py
rapidocr/rapidocr/networks/backbones/__init__.py
rapidocr/rapidocr/networks/backbones/det_mobilenet_v3.py
rapidocr/rapidocr/networks/backbones/rec_hgnet.py
rapidocr/rapidocr/networks/backbones/rec_lcnetv3.py
rapidocr/rapidocr/networks/backbones/rec_mobilenet_v3.py
rapidocr/rapidocr/networks/backbones/rec_svtrnet.py
rapidocr/rapidocr/networks/heads/__init__.py
rapidocr/rapidocr/networks/heads/cls_head.py
rapidocr/rapidocr/networks/heads/det_db_head.py
rapidocr/rapidocr/networks/heads/rec_ctc_head.py
rapidocr/rapidocr/networks/heads/rec_multi_head.py
rapidocr/rapidocr/networks/necks/__init__.py
rapidocr/rapidocr/networks/necks/db_fpn.py
rapidocr/rapidocr/networks/necks/intracl.py
rapidocr/rapidocr/networks/necks/rnn.py
ok_rapid_directml-2.0.12.dist-info/METADATA
ok_rapid_directml-2.0.12.dist-info/WHEEL
ok_rapid_directml-2.0.12.dist-info/entry_points.txt
ok_rapid_directml-2.0.12.dist-info/top_level.txt
ok_rapid_directml-2.0.12.dist-info/RECORD
